[
    {
        "SkillId": "gpKSiOtOXJ",
        "SkillName": "SkillName1"
    },
    {
        "SkillId": "sbpYqgRreI",
        "SkillName": "SkillName2"
    },
    {
        "SkillId": "NewpFKEQGs",
        "SkillName": "SkillName3"
    },
    {
        "SkillId": "tiZNpZnmnb",
        "SkillName": "SkillName4"
    },
    {
        "SkillId": "vSQVRDvsbg",
        "SkillName": "SkillName5"
    },
    {
        "SkillId": "JTrFVJJkYB",
        "SkillName": "SkillName6"
    },
    {
        "SkillId": "pKriWAIJbz",
        "SkillName": "SkillName7"
    },
    {
        "SkillId": "eWeLkytSFq",
        "SkillName": "SkillName8"
    },
    {
        "SkillId": "kBZzCgjDrP",
        "SkillName": "SkillName9"
    },
    {
        "SkillId": "kNEIRBQnFt",
        "SkillName": "SkillName10"
    },
    {
        "SkillId": "BOdxXDGiVR",
        "SkillName": "SkillName11"
    },
    {
        "SkillId": "proofWmCuS",
        "SkillName": "SkillName12"
    },
    {
        "SkillId": "otxwYQDofT",
        "SkillName": "SkillName13"
    },
    {
        "SkillId": "fRUEKoJKst",
        "SkillName": "SkillName14"
    },
    {
        "SkillId": "UDzITIOIPW",
        "SkillName": "SkillName15"
    },
    {
        "SkillId": "yRxpxpSomQ",
        "SkillName": "SkillName16"
    },
    {
        "SkillId": "YryUmgWnkt",
        "SkillName": "SkillName17"
    },
    {
        "SkillId": "GZCmUqWMjs",
        "SkillName": "SkillName18"
    },
    {
        "SkillId": "HMouoDDRLL",
        "SkillName": "SkillName19"
    },
    {
        "SkillId": "aEJwULlafY",
        "SkillName": "SkillName20"
    }
]